cacp/__init__.py
cacp/comparison.py
cacp/dataset.py
cacp/gui/__init__.py
cacp/gui/assets/__init__.py
cacp/gui/assets/dashAgGridComponentFunctions.js
cacp/gui/assets/datasets.csv
cacp/gui/assets/main.css
cacp/gui/assets/sidebar.js
cacp/gui/components/__init__.py
cacp/gui/components/classifiers/__init__.py
cacp/gui/components/classifiers/custom_classifiers_table.py
cacp/gui/components/classifiers/river_classifiers_table.py
cacp/gui/components/classifiers/sklearn_classifiers_table.py
cacp/gui/components/datasets/__init__.py
cacp/gui/components/datasets/custom_datasets_table.py
cacp/gui/components/datasets/keel_datasets_table.py
cacp/gui/components/datasets/river_datasets_table.py
cacp/gui/components/experiments/__init__.py
cacp/gui/components/experiments/details/__init__.py
cacp/gui/components/experiments/details/processor.py
cacp/gui/components/experiments/new/__init__.py
cacp/gui/components/experiments/new/form.py
cacp/gui/components/experiments/new/selected_classifiers_table.py
cacp/gui/components/experiments/new/selected_datasets_table.py
cacp/gui/components/experiments/new/selected_metrics_table.py
cacp/gui/components/experiments/new/selection_modal.py
cacp/gui/components/metrics/__init__.py
cacp/gui/components/metrics/custom_metrics_table.py
cacp/gui/components/metrics/river_metrics_table.py
cacp/gui/components/metrics/sklearn_metrics_table.py
cacp/gui/components/shared/__init__.py
cacp/gui/components/shared/sidebar.py
cacp/gui/components/shared/utils.py
cacp/gui/custom/__init__.py
cacp/gui/custom/classifiers/__init__.py
cacp/gui/custom/datasets/__init__.py
cacp/gui/custom/experiments/__init__.py
cacp/gui/custom/metrics/__init__.py
cacp/gui/db/__init__.py
cacp/gui/db/custom_classifiers.py
cacp/gui/db/custom_datasets.py
cacp/gui/db/custom_metrics.py
cacp/gui/db/experiments.py
cacp/gui/external/__init__.py
cacp/gui/external/classifier.py
cacp/gui/external/dataset.py
cacp/gui/external/metric.py
cacp/gui/external/river_library/__init__.py
cacp-1.0.4.dist-info/entry_points.txt
cacp-1.0.4.dist-info/LICENSE
cacp-1.0.4.dist-info/METADATA
cacp-1.0.4.dist-info/WHEEL
cacp-1.0.4.dist-info/RECORD
