Metadata-Version: 2.1
Name: cacp
Version: 1.0.4
Summary: 
Author: Sylwester Czmil
Author-email: sylwekczmil@gmail.com
Requires-Python: >=3.10.0,<3.13
Classifier: Programming Language :: Python :: 3
Classifier: Programming Language :: Python :: 3.10
Classifier: Programming Language :: Python :: 3.11
Requires-Dist: Jinja2 (>=3.1.2,<4.0.0)
Requires-Dist: dash-ace (>=0.2.1,<0.3.0)
Requires-Dist: dash-ag-grid (>=2.3.0,<3.0.0)
Requires-Dist: dash-bootstrap-components (>=1.5.0,<2.0.0)
Requires-Dist: dash-rjsf (>=0.0.4,<0.0.5)
Requires-Dist: dash[diskcache] (>=2.13.0,<3.0.0)
Requires-Dist: joblib (>=1.3.2,<2.0.0)
Requires-Dist: matplotlib (>=3.8.0,<4.0.0)
Requires-Dist: numpy (>=1.25.2,<2.0.0)
Requires-Dist: pandas (>=2.2.0,<3.0.0)
Requires-Dist: pydantic (>=1.10.12,<2.0.0)
Requires-Dist: river (>=0.21.0,<0.22.0)
Requires-Dist: scikit-learn (>=1.3.0,<2.0.0)
Requires-Dist: tinydb (>=4.8.0,<5.0.0)
Requires-Dist: tqdm (>=4.66.1,<5.0.0)
Requires-Dist: typing-extensions (>=4.7.1,<5.0.0)
